huaweicloudsdkcloudbuild/__init__.py
huaweicloudsdkcloudbuild/v3/__init__.py
huaweicloudsdkcloudbuild/v3/cloudbuild_async_client.py
huaweicloudsdkcloudbuild/v3/cloudbuild_client.py
huaweicloudsdkcloudbuild/v3/model/__init__.py
huaweicloudsdkcloudbuild/v3/model/build_step.py
huaweicloudsdkcloudbuild/v3/model/download_keystore_request.py
huaweicloudsdkcloudbuild/v3/model/download_keystore_response.py
huaweicloudsdkcloudbuild/v3/model/history_record.py
huaweicloudsdkcloudbuild/v3/model/history_record1.py
huaweicloudsdkcloudbuild/v3/model/job.py
huaweicloudsdkcloudbuild/v3/model/parameter_item.py
huaweicloudsdkcloudbuild/v3/model/run_job_request.py
huaweicloudsdkcloudbuild/v3/model/run_job_request_body.py
huaweicloudsdkcloudbuild/v3/model/run_job_response.py
huaweicloudsdkcloudbuild/v3/model/scm.py
huaweicloudsdkcloudbuild/v3/model/show_history_details_request.py
huaweicloudsdkcloudbuild/v3/model/show_history_details_response.py
huaweicloudsdkcloudbuild/v3/model/show_job_list_by_project_id_request.py
huaweicloudsdkcloudbuild/v3/model/show_job_list_by_project_id_response.py
huaweicloudsdkcloudbuild/v3/model/show_job_status_request.py
huaweicloudsdkcloudbuild/v3/model/show_job_status_response.py
huaweicloudsdkcloudbuild/v3/model/show_job_success_ratio_request.py
huaweicloudsdkcloudbuild/v3/model/show_job_success_ratio_response.py
huaweicloudsdkcloudbuild/v3/model/show_last_history_request.py
huaweicloudsdkcloudbuild/v3/model/show_last_history_response.py
huaweicloudsdkcloudbuild/v3/model/show_list_history_request.py
huaweicloudsdkcloudbuild/v3/model/show_list_history_response.py
huaweicloudsdkcloudbuild/v3/model/show_list_period_history_request.py
huaweicloudsdkcloudbuild/v3/model/show_list_period_history_response.py
huaweicloudsdkcloudbuild/v3/region/__init__.py
huaweicloudsdkcloudbuild/v3/region/cloudbuild_region.py
huaweicloudsdkcloudbuild-3.1.24.dist-info/LICENSE
huaweicloudsdkcloudbuild-3.1.24.dist-info/METADATA
huaweicloudsdkcloudbuild-3.1.24.dist-info/WHEEL
huaweicloudsdkcloudbuild-3.1.24.dist-info/top_level.txt
huaweicloudsdkcloudbuild-3.1.24.dist-info/RECORD
